{"id":20,"parent_id":12,"book_id":5,"content_id":1,"language_id":1,"display_order":20,"title":"Facsimile 3","subtitle":"","short_title":"Abr.","uri":"/scriptures/pgp/abr/fac-3","content":[[".bodyBlock",["div",{"id":"f1","uri":"/scriptures/pgp/abr/fac-3.f1","order":".000.2390"},[".title","A Facsimile from the Book of Abraham"],[".subtitle","No. 3"],["div",{"id":"f2","uri":"/scriptures/pgp/abr/fac-3.f2","order":".000.2391"},["ol.number",[".title","Explanation"],["li",{"uri":"/scriptures/pgp/abr/fac-3.1"},"Abraham sitting upon Pharaoh’s throne, by the politeness of the king, with a crown upon his head, representing the Priesthood, as emblematical of the grand Presidency in Heaven; with the scepter of justice and judgment in his hand."],["li",{"uri":"/scriptures/pgp/abr/fac-3.2"},"King Pharaoh, whose name is given in the characters above his head."],["li",{"uri":"/scriptures/pgp/abr/fac-3.3"},"Signifies Abraham in Egypt as given also in",["a.scriptureRef",{"href":"/scriptures/pgp/abr/fac-1"},"Figure 10 of Facsimile No. 1"],"."],["li",{"uri":"/scriptures/pgp/abr/fac-3.4"},"Prince of Pharaoh, King of Egypt, as written above the hand."],["li",{"uri":"/scriptures/pgp/abr/fac-3.5"},"Shulem, one of the king’s principal waiters, as represented by the characters above his hand."],["li",{"uri":"/scriptures/pgp/abr/fac-3.6"},"Olimlah, a slave belonging to the prince."]]],["div",{"id":"p7","uri":"/scriptures/pgp/abr/fac-3.p7","order":".000.2398"},"Abraham is reasoning upon the principles of Astronomy, in the king’s court."]]]],"refs":null}
