{"id":18,"parent_id":0,"book_id":9414,"content_id":1,"language_id":1,"display_order":18,"title":"Abound","subtitle":"","short_title":"Abound","uri":"/scriptures/triple-index/abound","content":[["div",{"id":"t1","uri":"/scriptures/triple-index/abound.t1","order":".000.040"},[".title",["b","Abound"]],[".reference","See also",["a.scriptureRef",{"href":"/scriptures/triple-index/abundance"},"Abundance"]],["div",{"id":"f2","uri":"/scriptures/triple-index/abound.f2","order":".000.041"},["ul.index",["li","always",["i","abounding"],"in good works:",["a.scriptureRef",{"href":"/scriptures/bofm/mosiah/5.15"},"Mosiah 5:15"],"; (",["a.scriptureRef",{"href":"/scriptures/bofm/alma/7.24"},"Alma 7:24"],";",["a.scriptureRef",{"href":"/scriptures/bofm/ether/12.4"},"Ether 12:4"],"; )"],["li","Nephites",["i","abound"],"in grace of God:",["a.scriptureRef",{"href":"/scriptures/bofm/mosiah/27.5"},["span.padWord","Mosiah"],"27:5"],";"]]]]],"refs":null}
