{"id":266,"parent_id":0,"book_id":8,"content_id":1,"language_id":1,"display_order":266,"title":"Charger","subtitle":"","short_title":"Charger","uri":"/scriptures/bd/charger","content":[["div",{"id":"t1","uri":"/scriptures/bd/charger.t1","order":".000.713"},[".title","Charger"],["div",{"id":"p1","uri":"/scriptures/bd/charger.p1","order":".000.714"},"A dish or large plate (",["a.scriptureRef",{"href":"/scriptures/ot/num/7.13"},"Num. 7:13"],";",["a.scriptureRef",{"href":"/scriptures/ot/ezra/1.9"},"Ezra 1:9"],";",["a.scriptureRef",{"href":"/scriptures/nt/matt/14.8"},"Matt. 14:8"],";",["a.scriptureRef",{"href":"/scriptures/nt/mark/6.25"},"Mark 6:25"],")."]]],"refs":null}
