{"id":1054,"parent_id":0,"book_id":7,"content_id":1,"language_id":1,"display_order":1054,"title":"Family, Children, Duties of","subtitle":"","short_title":"Family, Children, Duties of","uri":"/scriptures/tg/family-children-duties-of","content":[["div",{"id":"t1","uri":"/scriptures/tg/family-children-duties-of.t1","order":".000.3271"},[".title",["b","Family, Children, Duties of"]],[".reference","See also",["a.scriptureRef",{"href":"/scriptures/tg/family"},"Family"],";",["a.scriptureRef",{"href":"/scriptures/tg/genealogy-and-temple-work"},"Genealogy and Temple Work"],";",["a.scriptureRef",{"href":"/scriptures/tg/honoring-father-and-mother"},"Honoring Father and Mother"]],["div",{"id":"f2","uri":"/scriptures/tg/family-children-duties-of.f2","order":".000.3272"},["ul.index",["li",["i","Honour"],"thy father and thy mother:",["a.scriptureRef",{"href":"/scriptures/ot/ex/20.12"},"Ex. 20:12"],"; (",["a.scriptureRef",{"href":"/scriptures/nt/matt/19.19"},"Matt. 19:19"],";",["a.scriptureRef",{"href":"/scriptures/bofm/1-ne/17.55"},"1 Ne. 17:55"],";",["a.scriptureRef",{"href":"/scriptures/bofm/mosiah/13.20"},"Mosiah 13:20"],"; )"],["li","Thou shalt …",["i","honour"],"the face of the old man:",["a.scriptureRef",{"href":"/scriptures/ot/lev/19.32"},"Lev. 19:32"],";"],["li",["i","forsake not"],"the law of thy mother:",["a.scriptureRef",{"href":"/scriptures/ot/prov/1.8"},"Prov. 1:8"],";"],["li",["i","Hear"],"… the instruction of a father:",["a.scriptureRef",{"href":"/scriptures/ot/prov/4.1"},["span.padWord","Prov."],"4:1"],";"],["li",["i","keep"],"thy father’s commandment:",["a.scriptureRef",{"href":"/scriptures/ot/prov/6.20"},["span.padWord","Prov."],"6:20"],";"],["li",["i","Hearken"],"unto thy father:",["a.scriptureRef",{"href":"/scriptures/ot/prov/23.22"},["span.padWord","Prov."],"23:22"],";"],["li","A son",["i","honoureth"],"his father:",["a.scriptureRef",{"href":"/scriptures/ot/mal/1.6"},"Mal. 1:6"],";"]]],["div",{"id":"f3","uri":"/scriptures/tg/family-children-duties-of.f3","order":".000.3273"},["ul.index",["li","he … was",["i","subject"],"unto them:",["a.scriptureRef",{"href":"/scriptures/nt/luke/2.51"},"Luke 2:51"],";"],["li",["i","obey"],"your parents in the Lord:",["a.scriptureRef",{"href":"/scriptures/nt/eph/6.1"},"Eph. 6:1"],";"],["li",["i","obey"],"your parents in all things:",["a.scriptureRef",{"href":"/scriptures/nt/col/3.20"},"Col. 3:20"],";"]]],["div",{"id":"f4","uri":"/scriptures/tg/family-children-duties-of.f4","order":".000.3274"},["ul.index",["li",["i","worship"],"the Lord:",["a.scriptureRef",{"href":"/scriptures/bofm/1-ne/17.55"},"1 Ne. 17:55"],";"],["li","as a child doth",["i","submit"],"to his father:",["a.scriptureRef",{"href":"/scriptures/bofm/mosiah/3.19"},"Mosiah 3:19"],";"]]],[".reference","See also",["a.scriptureRef",{"href":"/scriptures/ot/lev/20.9"},"Lev. 20:9"],";",["a.scriptureRef",{"href":"/scriptures/ot/prov/10.1"},"Prov. 10:1"],";",["a.scriptureRef",{"href":"/scriptures/ot/prov/17.6"},["span.padWord","Prov."],"17:6"],";",["a.scriptureRef",{"href":"/scriptures/ot/mal/4.6"},"Mal. 4:6"],";",["a.scriptureRef",{"href":"/scriptures/nt/rom/1.30"},"Rom. 1:30"],";",["a.scriptureRef",{"href":"/scriptures/nt/2-tim/3.2"},"2 Tim. 3:2"],";",["a.scriptureRef",{"href":"/scriptures/bofm/morm/1.2"},"Morm. 1:2"],";",["a.scriptureRef",{"href":"/scriptures/dc-testament/dc/2.2"},"D&C 2:2"],";",["a.scriptureRef",{"href":"/scriptures/dc-testament/dc/128.18"},["span.padWord","D&C"],"128:18"],";",["a.scriptureRef",{"href":"/scriptures/pgp/js-h/1.38-39"},"JS—H 1:38–39"]]]],"refs":null}
