{"id":1824,"parent_id":0,"book_id":7,"content_id":1,"language_id":1,"display_order":1824,"title":"Line","subtitle":"","short_title":"Line","uri":"/scriptures/tg/line","content":[["div",{"id":"t1","uri":"/scriptures/tg/line.t1","order":".000.6096"},[".title",["b","Line"]],["div",{"id":"f1","uri":"/scriptures/tg/line.f1","order":".000.6097"},["ul.index",["li","who hath stretched the",["i","line"],"upon it:",["a.scriptureRef",{"href":"/scriptures/ot/job/38.5"},"Job 38:5"],";"],["li","precept upon precept;",["i","line"],"upon",["i","line"],":",["a.scriptureRef",{"href":"/scriptures/ot/isa/28.10"},"Isa. 28:10"],"; (",["a.scriptureRef",{"href":"/scriptures/bofm/2-ne/28.30"},"2 Ne. 28:30"],";",["a.scriptureRef",{"href":"/scriptures/dc-testament/dc/98.12"},"D&C 98:12"],";",["a.scriptureRef",{"href":"/scriptures/dc-testament/dc/128.21"},["span.padWord","D&C"],"128:21"],"; )"],["li","Judgment also will I lay to the",["i","line"],":",["a.scriptureRef",{"href":"/scriptures/ot/isa/28.17"},["span.padWord","Isa."],"28:17"],";"],["li","measuring",["i","line"],"shall yet go forth:",["a.scriptureRef",{"href":"/scriptures/ot/jer/31.39"},"Jer. 31:39"],";"],["li","when the man that had the",["i","line"],"in his hand went forth:",["a.scriptureRef",{"href":"/scriptures/ot/ezek/47.3"},"Ezek. 47:3"],";"],["li","a",["i","line"],"shall be stretched forth upon Jerusalem:",["a.scriptureRef",{"href":"/scriptures/ot/zech/1.16"},"Zech. 1:16"],";"],["li","a man with a measuring",["i","line"],":",["a.scriptureRef",{"href":"/scriptures/ot/zech/2.1"},["span.padWord","Zech."],"2:1"],";"]]],["div",{"id":"f2","uri":"/scriptures/tg/line.f2","order":".000.6098"},["ul.index",["li","boast in another man’s",["i","line"],"of things:",["a.scriptureRef",{"href":"/scriptures/nt/2-cor/10.16"},"2 Cor. 10:16"],";"]]]]],"refs":null}
