{"id":16,"parent_id":0,"book_id":22623,"content_id":1,"language_id":0,"display_order":16,"title":"On the Trail","subtitle":"","short_title":"On the Trail","uri":"/friend/2013/01/on-the-trail","content":[["div",{"id":"head1","uri":"/friend/2013/01/on-the-trail.head1"},[".title","On the Trail"]],[".bodyBlock",["div",{"id":"p2","uri":"/friend/2013/01/on-the-trail.p2"},"Come along as we explore some important places in Church history! On each story in our new series, you’ll find a small icon to cut out and paste on this map. Find this month’s story on",["span.crossRef","pages 4–5"],"."],["div",{"id":"f1","uri":"/friend/2013/01/on-the-trail.f1"},[".credit",["div",{"id":"p3","uri":"/friend/2013/01/on-the-trail.p3"},"Illustration by Taia Morley"]]]]],"refs":null}
