{"id":2832,"parent_id":0,"book_id":9414,"content_id":1,"language_id":1,"display_order":2832,"title":"Unlearned","subtitle":"","short_title":"Unlearned","uri":"/scriptures/triple-index/unlearned","content":[["div",{"id":"t1","uri":"/scriptures/triple-index/unlearned.t1","order":".000.7330"},[".title",["b","Unlearned"]],[".reference","See also",["a.scriptureRef",{"href":"/scriptures/triple-index/humble"},"Humble"],";",["a.scriptureRef",{"href":"/scriptures/triple-index/ignorance"},"Ignorance"],";",["a.scriptureRef",{"href":"/scriptures/triple-index/small"},"Small"],";",["a.scriptureRef",{"href":"/scriptures/triple-index/weak"},"Weak"]],["div",{"id":"f2","uri":"/scriptures/triple-index/unlearned.f2","order":".000.7331"},["ul.index",["li","those who are",["i","unlearned"],"shall thresh nations:",["a.scriptureRef",{"href":"/scriptures/dc-testament/dc/35.13"},"D&C 35:13"],";"]]]]],"refs":null}
