{"id":3307,"parent_id":0,"book_id":7,"content_id":1,"language_id":1,"display_order":3307,"title":"Uprightly","subtitle":"","short_title":"Uprightly","uri":"/scriptures/tg/uprightly","content":[["div",{"id":"t1","uri":"/scriptures/tg/uprightly.t1","order":".000.11510"},[".title",["b","Uprightly"]],[".reference","See also",["a.scriptureRef",{"href":"/scriptures/tg/righteously"},"Righteously"]],["div",{"id":"f2","uri":"/scriptures/tg/uprightly.f2","order":".000.11511"},["ul.index",["li","He that walketh",["i","uprightly"],"walketh surely:",["a.scriptureRef",{"href":"/scriptures/ot/prov/10.9"},"Prov. 10:9"],";"],["li","they abhor him that speaketh",["i","uprightly"],":",["a.scriptureRef",{"href":"/scriptures/ot/amos/5.10"},"Amos 5:10"],";"]]],["div",{"id":"f3","uri":"/scriptures/tg/uprightly.f3","order":".000.11512"},["ul.index",["li","give heed unto it, that ye might walk",["i","uprightly"],"before God:",["a.scriptureRef",{"href":"/scriptures/bofm/1-ne/16.3"},"1 Ne. 16:3"],"; (",["a.scriptureRef",{"href":"/scriptures/bofm/mosiah/18.29"},"Mosiah 18:29"],";",["a.scriptureRef",{"href":"/scriptures/bofm/alma/1.1"},"Alma 1:1"],"; )"]]],["div",{"id":"f4","uri":"/scriptures/tg/uprightly.f4","order":".000.11513"},["ul.index",["li","Joseph, to repent and walk more",["i","uprightly"],"before me:",["a.scriptureRef",{"href":"/scriptures/dc-testament/dc/5.21"},"D&C 5:21"],";"],["li","you must walk",["i","uprightly"],"before me:",["a.scriptureRef",{"href":"/scriptures/dc-testament/dc/18.31"},["span.padWord","D&C"],"18:31"],";"],["li","do in all holiness of heart, walking",["i","uprightly"],"before me:",["a.scriptureRef",{"href":"/scriptures/dc-testament/dc/46.7"},["span.padWord","D&C"],"46:7"],";"],["li","all things shall work together for good to them that walk",["i","uprightly"],":",["a.scriptureRef",{"href":"/scriptures/dc-testament/dc/100.15"},["span.padWord","D&C"],"100:15"],";"]]]]],"refs":null}
