{"id":331,"parent_id":0,"book_id":7,"content_id":1,"language_id":1,"display_order":331,"title":"Boast, Boasting","subtitle":"","short_title":"Boast, Boasting","uri":"/scriptures/tg/boast","content":[["div",{"id":"t1","uri":"/scriptures/tg/boast.t1","order":".000.935"},[".title",["b","Boast, Boasting"]],[".reference","See also",["a.scriptureRef",{"href":"/scriptures/tg/haughtiness"},"Haughtiness"],";",["a.scriptureRef",{"href":"/scriptures/tg/pride"},"Pride"]],["div",{"id":"f2","uri":"/scriptures/tg/boast.f2","order":".000.936"},["ul.index",["li","Let not him …",["i","boast"],"himself:",["a.scriptureRef",{"href":"/scriptures/ot/1-kgs/20.11"},"1 Kgs. 20:11"],";"],["li","wicked",["i","boasteth"],"of his heart’s desire:",["a.scriptureRef",{"href":"/scriptures/ot/ps/10.3"},"Ps. 10:3"],";"],["li","when he is gone his way, then he",["i","boasteth"],":",["a.scriptureRef",{"href":"/scriptures/ot/prov/20.14"},"Prov. 20:14"],";"],["li","Whoso",["i","boasteth"],"himself of a false gift:",["a.scriptureRef",{"href":"/scriptures/ot/prov/25.14"},["span.padWord","Prov."],"25:14"],";"],["li",["i","Boast"],"not thyself of to morrow:",["a.scriptureRef",{"href":"/scriptures/ot/prov/27.1"},["span.padWord","Prov."],"27:1"],";"],["li","Let another man",["i","praise"],"thee, and not thine own mouth:",["a.scriptureRef",{"href":"/scriptures/ot/prov/27.2"},["span.padWord","Prov."],"27:2"],";"],["li","Shall the axe",["i","boast"],"itself against him that heweth:",["a.scriptureRef",{"href":"/scriptures/ot/isa/10.15"},"Isa. 10:15"],"; (",["a.scriptureRef",{"href":"/scriptures/bofm/2-ne/20.15"},"2 Ne. 20:15"],"; )"]]],["div",{"id":"f3","uri":"/scriptures/tg/boast.f3","order":".000.937"},["ul.index",["li","haters of God, despiteful, proud,",["i","boasters"],":",["a.scriptureRef",{"href":"/scriptures/nt/rom/1.30"},"Rom. 1:30"],";"],["li",["i","Boast"],"not against the branches:",["a.scriptureRef",{"href":"/scriptures/nt/rom/11.18"},["span.padWord","Rom."],"11:18"],";"],["li","our",["i","boasting"],"… is found a truth:",["a.scriptureRef",{"href":"/scriptures/nt/2-cor/7.14"},"2 Cor. 7:14"],";"],["li","will not",["i","boast"],"of things without our measure:",["a.scriptureRef",{"href":"/scriptures/nt/2-cor/10.13"},["span.padWord","2 Cor."],"10:13"],";"],["li","not he that",["i","commendeth"],"himself is approved:",["a.scriptureRef",{"href":"/scriptures/nt/2-cor/10.18"},["span.padWord","2 Cor."],"10:18"],";"],["li","I may",["i","boast"],"myself a little:",["a.scriptureRef",{"href":"/scriptures/nt/2-cor/11.16"},["span.padWord","2 Cor."],"11:16"],";"],["li","Not of works, lest any man should",["i","boast"],":",["a.scriptureRef",{"href":"/scriptures/nt/eph/2.9"},"Eph. 2:9"],";"],["li","tongue is a little member, and",["i","boasteth"],"great things:",["a.scriptureRef",{"href":"/scriptures/nt/james/3.5"},"James 3:5"],";"],["li","ye rejoice in your",["i","boastings"],":",["a.scriptureRef",{"href":"/scriptures/nt/james/4.16"},["span.padWord","James"],"4:16"],";"]]],["div",{"id":"f4","uri":"/scriptures/tg/boast.f4","order":".000.938"},["ul.index",["li","not done these things that I might",["i","boast"],":",["a.scriptureRef",{"href":"/scriptures/bofm/mosiah/2.15"},"Mosiah 2:15"],";"],["li","they did",["i","boast"],"in their own strength:",["a.scriptureRef",{"href":"/scriptures/bofm/mosiah/11.19"},["span.padWord","Mosiah"],"11:19"],"; (",["a.scriptureRef",{"href":"/scriptures/bofm/hel/4.13"},"Hel. 4:13"],";",["a.scriptureRef",{"href":"/scriptures/bofm/morm/3.9-10"},"Morm. 3:9–10"],";",["a.scriptureRef",{"href":"/scriptures/bofm/morm/4.8"},["span.padWord","Morm."],"4:8"],";",["a.scriptureRef",{"href":"/scriptures/dc-testament/dc/3.4,13"},"D&C 3:4, 13"],"; )"],["li","he did rise up in great",["i","swelling"],"words:",["a.scriptureRef",{"href":"/scriptures/bofm/alma/30.31"},"Alma 30:31"],";"],["li","do not",["i","boast"],"in your own wisdom:",["a.scriptureRef",{"href":"/scriptures/bofm/alma/38.11"},["span.padWord","Alma"],"38:11"],";"],["li","that ye may not do these things that ye may",["i","boast"],":",["a.scriptureRef",{"href":"/scriptures/bofm/hel/5.8"},"Hel. 5:8"],";"],["li","how quick to",["i","boast"],", and do all manner of … iniquity:",["a.scriptureRef",{"href":"/scriptures/bofm/hel/12.5"},["span.padWord","Hel."],"12:5"],";"],["li","swell with great pride, unto",["i","boasting"],":",["a.scriptureRef",{"href":"/scriptures/bofm/hel/13.22"},["span.padWord","Hel."],"13:22"],";"],["li","some were lifted up unto pride and",["i","boastings"],":",["a.scriptureRef",{"href":"/scriptures/bofm/3-ne/6.10"},"3 Ne. 6:10"],";"]]],["div",{"id":"f5","uri":"/scriptures/tg/boast.f5","order":".000.939"},["ul.index",["li","neither with",["i","boasting"],"nor rejoicing, lest you be seized:",["a.scriptureRef",{"href":"/scriptures/dc-testament/dc/50.33"},"D&C 50:33"],";"],["li","they shall not",["i","boast"],"themselves:",["a.scriptureRef",{"href":"/scriptures/dc-testament/dc/84.73"},["span.padWord","D&C"],"84:73"],";"],["li","neither",["i","boast"],"of faith nor of mighty works:",["a.scriptureRef",{"href":"/scriptures/dc-testament/dc/105.24"},["span.padWord","D&C"],"105:24"],";"]]],[".reference","See also",["a.scriptureRef",{"href":"/scriptures/ot/ps/49.6"},"Ps. 49:6"],";",["a.scriptureRef",{"href":"/scriptures/ot/prov/10.19"},"Prov. 10:19"],";",["a.scriptureRef",{"href":"/scriptures/nt/1-cor/3.18"},"1 Cor. 3:18"],";",["a.scriptureRef",{"href":"/scriptures/nt/2-cor/12.1-11"},"2 Cor. 12:1–11"],";",["a.scriptureRef",{"href":"/scriptures/nt/2-pet/2.10"},"2 Pet. 2:10"],";",["a.scriptureRef",{"href":"/scriptures/pgp/moses/5.33"},"Moses 5:33"]]]],"refs":null}
