{"id":973,"parent_id":0,"book_id":8,"content_id":1,"language_id":1,"display_order":973,"title":"Pinnacle of the temple","subtitle":"","short_title":"Pinnacle of the temple","uri":"/scriptures/bd/pinnacle-of-the-temple","content":[["div",{"id":"t1","uri":"/scriptures/bd/pinnacle-of-the-temple.t1","order":".000.2679"},[".title","Pinnacle of the temple"],["div",{"id":"p1","uri":"/scriptures/bd/pinnacle-of-the-temple.p1","order":".000.2680"},["a.scriptureRef",{"href":"/scriptures/nt/matt/4.5"},"Matt. 4:5"],";",["a.scriptureRef",{"href":"/scriptures/nt/luke/4.9"},"Luke 4:9"],". It is uncertain what is meant; probably part of the roof of one of the temple porches overlooking the deep valley of the Kidron."]]],"refs":null}
