{"id":1090,"parent_id":0,"book_id":8,"content_id":1,"language_id":1,"display_order":1090,"title":"Selah","subtitle":"","short_title":"Selah","uri":"/scriptures/bd/selah","content":[["div",{"id":"t1","uri":"/scriptures/bd/selah.t1","order":".000.3590"},[".title","Selah"],["div",{"id":"p1","uri":"/scriptures/bd/selah.p1","order":".000.3591"},"(1) Ancient capital of Edom (",["a.scriptureRef",{"href":"/scriptures/ot/2-kgs/14.7"},"2 Kgs. 14:7"],";",["a.scriptureRef",{"href":"/scriptures/ot/isa/16.1"},"Isa. 16:1"],"); rendered “the rock” in",["a.scriptureRef",{"href":"/scriptures/ot/judg/1.36"},"Judg. 1:36"],";",["a.scriptureRef",{"href":"/scriptures/ot/2-chr/25.12"},"2 Chr. 25:12"],";",["a.scriptureRef",{"href":"/scriptures/ot/obad/1.3"},"Obad. 1:3"],". It was afterwards known as Petra. There are still important buildings there belonging to the Roman period."],["div",{"id":"p2","uri":"/scriptures/bd/selah.p2","order":".000.3592"},"(2) A musical term that occurs 71 times in the Psalms and three times in Habakkuk. Its meaning is uncertain. Most likely it is a direction to the musicians to strike up, either with a louder accompaniment or with an interlude while the singing ceased."]]],"refs":null}
