{"id":1734,"parent_id":0,"book_id":9414,"content_id":1,"language_id":1,"display_order":1734,"title":"Moron, Land of","subtitle":"","short_title":"Moron, Land of","uri":"/scriptures/triple-index/moron-land-of","content":[["div",{"id":"t1","uri":"/scriptures/triple-index/moron-land-of.t1","order":".000.4418"},[".title",["b","Moron, Land of"],"—",["i","near the land of Desolation"]],["div",{"id":"f1","uri":"/scriptures/triple-index/moron-land-of.f1","order":".000.4419"},["ul.index",["li","is invaded by Corihor",["sup","1"],", king taken captive:",["a.scriptureRef",{"href":"/scriptures/bofm/ether/7.5-6"},"Ether 7:5–6"],";"],["li","is near Desolation:",["a.scriptureRef",{"href":"/scriptures/bofm/ether/7.6"},["span.padWord","Ether"],"7:6"],";"],["li","Shule is carried captive into",["i","Moron"],":",["a.scriptureRef",{"href":"/scriptures/bofm/ether/7.17"},["span.padWord","Ether"],"7:17"],";"],["li","brother of Shared places himself on throne of Coriantumr",["sup","2"],"in",["i","Moron"],":",["a.scriptureRef",{"href":"/scriptures/bofm/ether/14.6"},["span.padWord","Ether"],"14:6"],";"],["li","Coriantumr",["sup","2"],"battles Lib",["sup","2"],"in",["i","Moron"],":",["a.scriptureRef",{"href":"/scriptures/bofm/ether/14.11"},["span.padWord","Ether"],"14:11"],";"]]]]],"refs":null}
