{"id":92,"parent_id":90,"book_id":9,"content_id":1,"language_id":1,"display_order":92,"title":"JST, Revelations 2","subtitle":"","short_title":"JST, Rev.","uri":"/scriptures/jst/jst-rev/2","content":[[".bodyBlock",["div",{"id":"t1","uri":"/scriptures/jst/jst-rev/2.t1","order":"12.26.002.581"},[".title",["b","JST, Revelation 2:26–27."],"Compare",["a.scriptureRef",{"href":"/scriptures/nt/rev/2.26-27"},"Revelation 2:26–27"]],["div",{"id":"26","uri":"/scriptures/jst/jst-rev/2.26","order":".002.582"},["b","26"],"And",["i","to him who"],"overcometh, and keepeth my",["i","commandments"],"unto the end, will I give power over",["i","many kingdoms;"]],["div",{"id":"27","uri":"/scriptures/jst/jst-rev/2.27","order":".002.583"},["b","27"],"And he shall rule them with",["i","the word of God; and they shall be in his hands"],"as the vessels",["i","of clay in the hands"],"of a potter;",["i","and he shall govern them by faith, with equity and justice,"],"even as I received of my Father."]]]],"refs":null}
